mirrors/__init__.py
mirrors/admin.py
mirrors/apps.py
mirrors/migrations/__init__.py
mirrors/models.py
mirrors/templates/mirrors.html
mirrors/tests.py
mirrors/urls.py
mirrors/views.py
django_mirrors-1.0.3.dist-info/METADATA
django_mirrors-1.0.3.dist-info/WHEEL
django_mirrors-1.0.3.dist-info/RECORD
